llm_integration/__init__.py
llm_integration/base.py
llm_integration/clients.py
llm_integration-0.1.0.dist-info/METADATA
llm_integration-0.1.0.dist-info/WHEEL
llm_integration-0.1.0.dist-info/top_level.txt
llm_integration-0.1.0.dist-info/RECORD
