Metadata-Version: 2.4
Name: llm_integration
Version: 0.1.0
Requires-Python: >=3.10
Requires-Dist: pydantic
Requires-Dist: backoff
Requires-Dist: ollama
Requires-Dist: openai
Dynamic: requires-dist
Dynamic: requires-python
